{
        "st1": {
            "id": "1",
            "name": "Sant Julià de Lòria",
            "shortname": "Sant Julià de Lòria",
            "link": "",
            "comment": "",
            "image": "",
            "color_map": "#7798bb",
            "color_map_over": "#366CA3"
        },
        "st2": {
            "id": "2",
            "name": "Escaldes-Engordany",
            "shortname": "Escaldes-Engordany",
            "link": "",
            "comment": "",
            "image": "",
            "color_map": "#7798bb",
            "color_map_over": "#366CA3"
        },
        "st3": {
            "id": "3",
            "name": "Andorra la Vella",
            "shortname": "Andorra la Vella",
            "link": "",
            "comment": "",
            "image": "",
            "color_map": "#7798bb",
            "color_map_over": "#366CA3"
        },
        "st4": {
            "id": "4",
            "name": "Encamp",
            "shortname": "Encamp",
            "link": "",
            "comment": "",
            "image": "",
            "color_map": "#7798bb",
            "color_map_over": "#366CA3"
        },
        "st5": {
            "id": "5",
            "name": "La Massana",
            "shortname": "La Massana",
            "link": "",
            "comment": "",
            "image": "",
            "color_map": "#7798bb",
            "color_map_over": "#366CA3"
        },
        "st6": {
            "id": "6",
            "name": "Canillo",
            "shortname": "Canillo",
            "link": "",
            "comment": "",
            "image": "",
            "color_map": "#7798bb",
            "color_map_over": "#366CA3"
        },
        "st7": {
            "id": "7",
            "name": "Ordino",
            "shortname": "Ordino",
            "link": "",
            "comment": "",
            "image": "",
            "color_map": "#7798bb",
            "color_map_over": "#366CA3"
        }
}