{
    "st1": {
        "id": 1,
        "name": "Altenburger Land",
        "shortname": "",
        "link": "",
        "comment": "",
        "image": "",
        "color_map": "#7798bb",
        "color_map_over": "#366CA3"
    },
    "st2": {
        "id": 2,
        "name": "Eichsfeld",
        "shortname": "",
        "link": "",
        "comment": "",
        "image": "",
        "color_map": "#7798bb",
        "color_map_over": "#366CA3"
    },
    "st3": {
        "id": 3,
        "name": "Eisenach",
        "shortname": "",
        "link": "",
        "comment": "",
        "image": "",
        "color_map": "#7798bb",
        "color_map_over": "#366CA3"
    },
    "st4": {
        "id": 4,
        "name": "Erfurt",
        "shortname": "",
        "link": "",
        "comment": "",
        "image": "",
        "color_map": "#7798bb",
        "color_map_over": "#366CA3"
    },
    "st5": {
        "id": 5,
        "name": "Gera",
        "shortname": "",
        "link": "",
        "comment": "",
        "image": "",
        "color_map": "#7798bb",
        "color_map_over": "#366CA3"
    },
    "st6": {
        "id": 6,
        "name": "Gotha",
        "shortname": "",
        "link": "",
        "comment": "",
        "image": "",
        "color_map": "#7798bb",
        "color_map_over": "#366CA3"
    },
    "st7": {
        "id": 7,
        "name": "Greiz",
        "shortname": "",
        "link": "",
        "comment": "",
        "image": "",
        "color_map": "#7798bb",
        "color_map_over": "#366CA3"
    },
    "st8": {
        "id": 8,
        "name": "Hildburghausen",
        "shortname": "",
        "link": "",
        "comment": "",
        "image": "",
        "color_map": "#7798bb",
        "color_map_over": "#366CA3"
    },
    "st9": {
        "id": 9,
        "name": "Ilm-Kreis",
        "shortname": "",
        "link": "",
        "comment": "",
        "image": "",
        "color_map": "#7798bb",
        "color_map_over": "#366CA3"
    },
    "st10": {
        "id": 10,
        "name": "Jena",
        "shortname": "",
        "link": "",
        "comment": "",
        "image": "",
        "color_map": "#7798bb",
        "color_map_over": "#366CA3"
    },
    "st11": {
        "id": 11,
        "name": "Kyffhäuserkreis",
        "shortname": "",
        "link": "",
        "comment": "",
        "image": "",
        "color_map": "#7798bb",
        "color_map_over": "#366CA3"
    },
    "st12": {
        "id": 12,
        "name": "Nordhausen",
        "shortname": "",
        "link": "",
        "comment": "",
        "image": "",
        "color_map": "#7798bb",
        "color_map_over": "#366CA3"
    },
    "st13": {
        "id": 13,
        "name": "Saale-Holzland-Kreis",
        "shortname": "",
        "link": "",
        "comment": "",
        "image": "",
        "color_map": "#7798bb",
        "color_map_over": "#366CA3"
    },
    "st14": {
        "id": 14,
        "name": "Saale-Orla-Kreis",
        "shortname": "",
        "link": "",
        "comment": "",
        "image": "",
        "color_map": "#7798bb",
        "color_map_over": "#366CA3"
    },
    "st15": {
        "id": 15,
        "name": "Saalfeld-Rudolstadt",
        "shortname": "",
        "link": "",
        "comment": "",
        "image": "",
        "color_map": "#7798bb",
        "color_map_over": "#366CA3"
    },
    "st16": {
        "id": 16,
        "name": "Schmalkalden-Meiningen",
        "shortname": "",
        "link": "",
        "comment": "",
        "image": "",
        "color_map": "#7798bb",
        "color_map_over": "#366CA3"
    },
    "st17": {
        "id": 17,
        "name": "Sömmerda",
        "shortname": "",
        "link": "",
        "comment": "",
        "image": "",
        "color_map": "#7798bb",
        "color_map_over": "#366CA3"
    },
    "st18": {
        "id": 18,
        "name": "Sonneberg",
        "shortname": "",
        "link": "",
        "comment": "",
        "image": "",
        "color_map": "#7798bb",
        "color_map_over": "#366CA3"
    },
    "st19": {
        "id": 19,
        "name": "Suhl",
        "shortname": "",
        "link": "",
        "comment": "",
        "image": "",
        "color_map": "#7798bb",
        "color_map_over": "#366CA3"
    },
    "st20": {
        "id": 20,
        "name": "Unstrut-Hainich-Kreis",
        "shortname": "",
        "link": "",
        "comment": "",
        "image": "",
        "color_map": "#7798bb",
        "color_map_over": "#366CA3"
    },
    "st21": {
        "id": 21,
        "name": "Wartburgkreis",
        "shortname": "",
        "link": "",
        "comment": "",
        "image": "",
        "color_map": "#7798bb",
        "color_map_over": "#366CA3"
    },
    "st22": {
        "id": 22,
        "name": "Weimar",
        "shortname": "",
        "link": "",
        "comment": "",
        "image": "",
        "color_map": "#7798bb",
        "color_map_over": "#366CA3"
    },
    "st23": {
        "id": 23,
        "name": "Weimarer Land",
        "shortname": "",
        "link": "",
        "comment": "",
        "image": "",
        "color_map": "#7798bb",
        "color_map_over": "#366CA3"
    }
}